user_g11n/__init__.py
user_g11n/apps.py
user_g11n/factories.py
user_g11n/middleware.py
user_g11n/models.py
user_g11n/utils.py
user_g11n/views.py
django_user_g11n-0.4.4.dist-info/AUTHORS.md
django_user_g11n-0.4.4.dist-info/LICENSE
django_user_g11n-0.4.4.dist-info/METADATA
django_user_g11n-0.4.4.dist-info/WHEEL
django_user_g11n-0.4.4.dist-info/top_level.txt
django_user_g11n-0.4.4.dist-info/RECORD
