Metadata-Version: 2.1
Name: django-user-g11n
Version: 0.4.4
Summary: User g11n extension for Django
Home-page: https://github.com/salexkidd/django-user-g11n
Author: salexkidd
Author-email: salexkidd@gmail.com
Keywords: django,i18n,l10n,g11n,timezone
Classifier: Development Status :: 5 - Production/Stable
Classifier: Environment :: Web Environment
Classifier: Framework :: Django
Classifier: Intended Audience :: Developers
Classifier: License :: OSI Approved :: MIT License
Classifier: Operating System :: OS Independent
Classifier: Programming Language :: Python
Classifier: Programming Language :: Python :: 3
Classifier: Topic :: Internet :: WWW/HTTP
Classifier: Topic :: Internet :: WWW/HTTP :: Dynamic Content
License-File: LICENSE
License-File: AUTHORS.md
